tedent/__init__.py
tedent/_vendor/__init__.py
tedent/_vendor/ordered_set-3.1.1-py3.7.egg-info/PKG-INFO
tedent/_vendor/ordered_set-3.1.1-py3.7.egg-info/SOURCES.txt
tedent/_vendor/ordered_set-3.1.1-py3.7.egg-info/dependency_links.txt
tedent/_vendor/ordered_set-3.1.1-py3.7.egg-info/installed-files.txt
tedent/_vendor/ordered_set-3.1.1-py3.7.egg-info/top_level.txt
tedent/_vendor/ordered_set.py
tedent/_vendor/wrapt/__init__.py
tedent/_vendor/wrapt/_wrappers.cpython-37m-x86_64-linux-gnu.so
tedent/_vendor/wrapt/decorators.py
tedent/_vendor/wrapt/importer.py
tedent/_vendor/wrapt/wrappers.py
tedent/_vendor/wrapt-1.11.1.dist-info/INSTALLER
tedent/_vendor/wrapt-1.11.1.dist-info/LICENSE
tedent/_vendor/wrapt-1.11.1.dist-info/METADATA
tedent/_vendor/wrapt-1.11.1.dist-info/RECORD
tedent/_vendor/wrapt-1.11.1.dist-info/WHEEL
tedent/_vendor/wrapt-1.11.1.dist-info/top_level.txt
tedent/fns/__init__.py
tedent/fns/all_.py
tedent/fns/decorators/__init__.py
tedent/fns/decorators/argIsCallable.py
tedent/fns/decorators/argIsClass.py
tedent/fns/decorators/argIsListOfType.py
tedent/fns/decorators/argIsType.py
tedent/fns/discardFirst.py
tedent/fns/discardLastWhile.py
tedent/fns/forEach.py
tedent/fns/iif.py
tedent/fns/internal/__init__.py
tedent/fns/internal/discardWhen.py
tedent/fns/internal/get.py
tedent/fns/internal/getArgName.py
tedent/fns/internal/getFnSignature.py
tedent/fns/internal/getNumPositionalParams.py
tedent/fns/internal/getTypedResult.py
tedent/fns/internal/iif.py
tedent/fns/internal/isLaden.py
tedent/fns/internal/isOnlyWhitespace.py
tedent/fns/internal/isType.py
tedent/fns/internal/joinWith.py
tedent/fns/internal/makeCallFn.py
tedent/fns/internal/makeGenericCallFn.py
tedent/fns/internal/map_.py
tedent/fns/internal/passThrough.py
tedent/fns/internal/raise_.py
tedent/fns/internal/reduce.py
tedent/fns/internal/returnFirstArgument.py
tedent/fns/internal/sanitizeAscDesc.py
tedent/fns/internal/sort.py
tedent/fns/internal/toType.py
tedent/fns/invokeAttr.py
tedent/fns/isEmpty.py
tedent/fns/joinWith.py
tedent/fns/passThrough.py
tedent/fns/raise_.py
tedent/indentWith.py
tedent/index.py
tedent/invalid.py
tedent/license.txt
tedent/top_level.txt
tedent/utils.py
tedent-0.1.4.dist-info/WHEEL
tedent-0.1.4.dist-info/METADATA
tedent-0.1.4.dist-info/RECORD
