Metadata-Version: 2.1
Name: tedent
Version: 0.1.4
Summary: like dedent but more flexible
Home-page: https://github.com/olsonpm/py_tedent
Author: Philip Olson
Author-email: philip.olson@pm.me
Requires-Python: >=3.7,<4.0
Classifier: Programming Language :: Python :: 3
Classifier: Programming Language :: Python :: 3.7
Project-URL: Repository, https://github.com/olsonpm/py_tedent
